logalpha/__init__.py
logalpha/__meta__.py
logalpha/color.py
logalpha/handler.py
logalpha/level.py
logalpha/logger.py
logalpha/message.py
logalpha/contrib/__init__.py
logalpha/contrib/ok.py
logalpha/contrib/simple.py
logalpha/contrib/standard.py
logalpha-3.0.0.dist-info/LICENSE
logalpha-3.0.0.dist-info/METADATA
logalpha-3.0.0.dist-info/WHEEL
logalpha-3.0.0.dist-info/entry_points.txt
logalpha-3.0.0.dist-info/top_level.txt
logalpha-3.0.0.dist-info/RECORD
