Metadata-Version: 2.1
Name: logalpha
Version: 3.0.0
Summary: A minimal framework for logging in Python.
Home-page: https://logalpha.readthedocs.io
Author: Geoffrey Lentner
Author-email: <glentner@purdue.edu>
License: Apache Software License
Keywords: python minimalist logging framework
Platform: UNKNOWN
Classifier: Development Status :: 5 - Production/Stable
Classifier: Topic :: System :: Logging
Classifier: Programming Language :: Python :: 3.7
Classifier: Programming Language :: Python :: 3.8
Classifier: Programming Language :: Python :: 3.9
Classifier: License :: OSI Approved :: Apache Software License
